<?xml version="1.0" encoding="utf-8" ?>
<TLPLSEA>
  <TLPL>
    <Detail>
      <t1>1</t1>
        </Detail>
    </TLPL>
  <TLPL>
     <Detail>
       <t1>2</t1>
     </Detail>
  </TLPL>
  <TLPL>
    <Detail>
      <t1>3</t1>
    </Detail>
  </TLPL>
  <TLPL>
    <Detail>
      <t1>4</t1>
    </Detail>
  </TLPL>
  <TLPL>
    <Detail>
      <t1>5</t1>
    </Detail>
  </TLPL>
  <TLPL>
    <Detail>
      <t1>6</t1>
    </Detail>
  </TLPL>
  <TLPL>
    <Detail>
      <t1>7</t1>
    </Detail>
  </TLPL>
  <TLPL>
    <Detail>
      <t1>8</t1>
    </Detail>
  </TLPL>
  <TLPL>
    <Detail>
      <t1>9</t1>
    </Detail>
  </TLPL>
  <TLPL>
    <Detail>
      <t1>10</t1>
    </Detail>
  </TLPL>
  <TLPL>
    <Detail>
      <t1>11</t1>
    </Detail>
  </TLPL>
  <TLPL>
    <Detail>
      <t1>12</t1>
    </Detail>
  </TLPL>
  <TLPL>
    <Detail>
      <t1>13</t1>
    </Detail>
  </TLPL>
  <TLPL>
    <Detail>
      <t1>14</t1>
    </Detail>
  </TLPL>
  <TLPL>
    <Detail>
      <t1>15</t1>
    </Detail>
  </TLPL>
  <TLPL>
    <Detail>
      <t1>16</t1>
    </Detail>
  </TLPL>
  <TLPL>
    <Detail>
      <t1>17</t1>
    </Detail>
  </TLPL>
  <TLPL>
    <Detail>
      <t1>18</t1>
    </Detail>
  </TLPL>
  <TLPL>
    <Detail>
      <t1>19</t1>
    </Detail>
  </TLPL>
  <TLPL>
    <Detail>
      <t1>20</t1>
    </Detail>
  </TLPL>
  <TLPL>
    <Detail>
      <t1>21</t1>
    </Detail>
  </TLPL>
  <TLPL>
    <Detail>
      <t1>22</t1>
    </Detail>
  </TLPL>
  <TLPL>
    <Detail>
      <t1>23</t1>
    </Detail>
  </TLPL>
  <TLPL>
    <Detail>
      <t1>24</t1>
    </Detail>
  </TLPL>
  <TLPL>
    <Detail>
      <t1>25</t1>
    </Detail>
  </TLPL>
  <TLPL>
    <Detail>
      <t1>26</t1>
    </Detail>
  </TLPL>
  <TLPL>
    <Detail>
      <t1>27</t1>
    </Detail>
  </TLPL>
  <TLPL>
    <Detail>
      <t1>28</t1>
    </Detail>
  </TLPL>
  <TLPL>
    <Detail>
      <t1>29</t1>
    </Detail>
  </TLPL>
  <TLPL>
    <Detail>
      <t1>30</t1>
    </Detail>
  </TLPL>
  <TLPL>
    <Detail>
      <t1>31</t1>
    </Detail>
  </TLPL>
  <TLPL>
    <Detail>
      <t1>32</t1>
    </Detail>
  </TLPL>
  <TLPL>
    <Detail>
      <t1>33</t1>
    </Detail>
  </TLPL>
  <TLPL>
    <Detail>
      <t1>34</t1>
    </Detail>
  </TLPL>
  <TLPL>
    <Detail>
      <t1>35</t1>
    </Detail>
  </TLPL>
  <TLPL>
    <Detail>
      <t1>36</t1>
    </Detail>
  </TLPL>
  <TLPL>
    <Detail>
      <t1>37</t1>
    </Detail>
  </TLPL>
  <TLPL>
    <Detail>
      <t1>38</t1>
    </Detail>
  </TLPL>
  <TLPL>
    <Detail>
      <t1>39</t1>
    </Detail>
  </TLPL>
  <TLPL>
    <Detail>
      <t1>40</t1>
    </Detail>
  </TLPL>
  <TLPL>
    <Detail>
      <t1>41</t1>
    </Detail>
  </TLPL>
  <TLPL>
    <Detail>
      <t1>42</t1>
    </Detail>
  </TLPL>
  <TLPL>
    <Detail>
      <t1>43</t1>
    </Detail>
  </TLPL>
  <TLPL>
    <Detail>
      <t1>44</t1>
    </Detail>
  </TLPL>
  <TLPL>
    <Detail>
      <t1>45</t1>
    </Detail>
  </TLPL>
  <TLPL>
    <Detail>
      <t1>46</t1>
    </Detail>
  </TLPL>
  <TLPL>
    <Detail>
      <t1>47</t1>
    </Detail>
  </TLPL>
  <TLPL>
    <Detail>
      <t1>48</t1>
    </Detail>
  </TLPL>
  <TLPL>
    <Detail>
      <t1>49</t1>
    </Detail>
  </TLPL>
  <TLPL>
    <Detail>
      <t1>50</t1>
    </Detail>
  </TLPL>
</TLPLSEA>
